hockey_blast_common_lib/__init__.py
hockey_blast_common_lib/aggregate_all_stats.py
hockey_blast_common_lib/aggregate_goalie_stats.py
hockey_blast_common_lib/aggregate_h2h_stats.py
hockey_blast_common_lib/aggregate_human_stats.py
hockey_blast_common_lib/aggregate_referee_stats.py
hockey_blast_common_lib/aggregate_s2s_stats.py
hockey_blast_common_lib/aggregate_scorekeeper_stats.py
hockey_blast_common_lib/aggregate_skater_stats.py
hockey_blast_common_lib/aggregate_team_goalie_stats.py
hockey_blast_common_lib/aggregate_team_skater_stats.py
hockey_blast_common_lib/assign_skater_skill.py
hockey_blast_common_lib/db_connection.py
hockey_blast_common_lib/dump_sample_db.sh
hockey_blast_common_lib/embedding_utils.py
hockey_blast_common_lib/h2h_models.py
hockey_blast_common_lib/hockey_blast_sample_backup.sql.gz
hockey_blast_common_lib/models.py
hockey_blast_common_lib/options.py
hockey_blast_common_lib/progress_utils.py
hockey_blast_common_lib/restore_sample_db.sh
hockey_blast_common_lib/skills_in_divisions.py
hockey_blast_common_lib/skills_propagation.py
hockey_blast_common_lib/stats_models.py
hockey_blast_common_lib/stats_utils.py
hockey_blast_common_lib/utils.py
hockey_blast_common_lib/wsgi.py
hockey_blast_common_lib-0.1.66.dist-info/METADATA
hockey_blast_common_lib-0.1.66.dist-info/WHEEL
hockey_blast_common_lib-0.1.66.dist-info/top_level.txt
hockey_blast_common_lib-0.1.66.dist-info/RECORD
