Metadata-Version: 2.1
Name: hockey-blast-common-lib
Version: 0.1.66
Summary: Common library for shared functionality and DB models
Author: Pavel Kletskov
Author-email: kletskov@gmail.com
Requires-Python: >=3.7
Requires-Dist: setuptools
Requires-Dist: Flask-SQLAlchemy
Requires-Dist: SQLAlchemy
Requires-Dist: requests
